sllm/__init__.py
llm_profiler-0.0.0.dist-info/LICENSE
llm_profiler-0.0.0.dist-info/METADATA
llm_profiler-0.0.0.dist-info/WHEEL
llm_profiler-0.0.0.dist-info/top_level.txt
llm_profiler-0.0.0.dist-info/RECORD
